LICENSE
MANIFEST.in
README.rst
example.py
setup.py
ass/__init__.py
ass.ets.egg-info/PKG-INFO
ass.ets.egg-info/SOURCES.txt
ass.ets.egg-info/dependency_links.txt
ass.ets.egg-info/requires.txt
ass.ets.egg-info/top_level.txt
ass/ets/__init__.py
ass/ets/bundles.py
ass/ets/dicts.py
ass/ets/options.py
ass/ets/workers.py
ass/ets/filters/__init__.py
ass/ets/filters/builtin.py
ass/ets/filters/getreal.py