Metadata-Version: 1.0
Name: ass.ets
Version: 0.1.1
Summary: Asset management for webapps.
Home-page: http://github.com/kaste/ass.ets
Author: herr kaste
Author-email: herr.kaste@gmail.com
License: UNKNOWN
Download-URL: http://github.com/kaste/ass.ets/tarball/master#egg=ass.ets-dev
Platform: UNKNOWN
Classifier: Development Status :: 4 - Beta
Classifier: Environment :: Web Environment
Classifier: Intended Audience :: Developers
Classifier: License :: OSI Approved :: BSD License
Classifier: Operating System :: OS Independent
Classifier: Programming Language :: Python
Classifier: Topic :: Internet :: WWW/HTTP
Classifier: Topic :: Software Development :: Libraries
